MANIFEST.in
README.rst
requirements.txt
setup.cfg
setup.py
django_xss_cleaner.egg-info/PKG-INFO
django_xss_cleaner.egg-info/SOURCES.txt
django_xss_cleaner.egg-info/dependency_links.txt
django_xss_cleaner.egg-info/not-zip-safe
django_xss_cleaner.egg-info/requires.txt
django_xss_cleaner.egg-info/top_level.txt
xss_cleaner/__init__.py
xss_cleaner/decorators.py
xss_cleaner/middlewares.py
xss_cleaner/settings.py
xss_cleaner/tests.py
xss_cleaner/urls.py
xss_cleaner/utils.py
xss_cleaner/views.py