Metadata-Version: 1.1
Name: django-xss-cleaner
Version: 1.0.1
Summary: clean xss
Home-page: https://pypi.org/simple/
Author: shaowenchen
Author-email: email@chenshaowen.com
License: BSD License
Keywords: xss
Platform: UNKNOWN
Classifier: Environment :: Web Environment
Classifier: Intended Audience :: Developers
Classifier: License :: OSI Approved :: BSD License
Classifier: Operating System :: OS Independent
Classifier: Programming Language :: Python
Classifier: Programming Language :: Python :: 2
Classifier: Programming Language :: Python :: 2.7
Classifier: Topic :: Internet :: WWW/HTTP
Classifier: Topic :: Internet :: WWW/HTTP :: Dynamic Content
